odoo/addons/mail_debrand/README.rst
odoo/addons/mail_debrand/__init__.py
odoo/addons/mail_debrand/__manifest__.py
odoo/addons/mail_debrand/data/ir_config_parameter.xml
odoo/addons/mail_debrand/i18n/es.po
odoo/addons/mail_debrand/i18n/fr.po
odoo/addons/mail_debrand/i18n/fr_FR.po
odoo/addons/mail_debrand/i18n/it.po
odoo/addons/mail_debrand/i18n/mail_debrand.pot
odoo/addons/mail_debrand/i18n/nl.po
odoo/addons/mail_debrand/i18n/pt.po
odoo/addons/mail_debrand/i18n/sl.po
odoo/addons/mail_debrand/i18n/sr_Latn.po
odoo/addons/mail_debrand/i18n/sv.po
odoo/addons/mail_debrand/models/__init__.py
odoo/addons/mail_debrand/models/mail_mail.py
odoo/addons/mail_debrand/models/mail_render_mixin.py
odoo/addons/mail_debrand/readme/CONTRIBUTORS.rst
odoo/addons/mail_debrand/readme/DESCRIPTION.rst
odoo/addons/mail_debrand/readme/HISTORY.rst
odoo/addons/mail_debrand/readme/USAGE.rst
odoo/addons/mail_debrand/static/description/icon.png
odoo/addons/mail_debrand/static/description/icon.svg
odoo/addons/mail_debrand/static/description/index.html
odoo/addons/mail_debrand/tests/__init__.py
odoo/addons/mail_debrand/tests/test_mail_debrand.py
odoo/addons/mail_debrand/tests/test_mail_debrand_digest.py
odoo14_addon_mail_debrand-14.0.2.2.4.dist-info/METADATA
odoo14_addon_mail_debrand-14.0.2.2.4.dist-info/WHEEL
odoo14_addon_mail_debrand-14.0.2.2.4.dist-info/top_level.txt
odoo14_addon_mail_debrand-14.0.2.2.4.dist-info/RECORD
