Metadata-Version: 2.1
Name: odoo14-addon-mail-debrand
Version: 14.0.2.2.4
Summary: Remove Odoo branding in sent emails Removes anchor <a href odoo.com togheder with it's parent ( for powerd by) form all the templates removes any 'odoo' that are in tempalte texts > 20characters
Home-page: https://github.com/OCA/social
Author: Tecnativa, ForgeFlow, Onestein, Sodexis, Nexterp Romania, Odoo Community Association (OCA)
Author-email: support@odoo-community.org
License: AGPL-3
Platform: UNKNOWN
Classifier: Programming Language :: Python
Classifier: Framework :: Odoo
Classifier: Framework :: Odoo :: 14.0
Classifier: License :: OSI Approved :: GNU Affero General Public License v3
Classifier: Development Status :: 5 - Production/Stable
Requires-Python: >=3.6
Requires-Dist: odoo <14.1dev,>=14.0a
